{"2bTqOs0qAtGvJFegi3mudP": {"name": "Y1 Mardel", "genres": [], "popularity": 7}, "3zJepdAr8wzLT4EL6fSieR": {"name": "Y1640", "genres": ["deconstructed club", "grimewave"], "popularity": 14}, "7dzSsCnqsvFaw9apNM19Ie": {"name": "Y1 Boujee", "genres": [], "popularity": 0}, "1neH9yawC4ZjsZUOwuBqkb": {"name": "Y1", "genres": [], "popularity": 2}, "6Pp8VUpf8qniKAbP5B2fx2": {"name": "Y15WHELL", "genres": [], "popularity": 4}, "040p95syNkSvFY5XyEx6f1": {"name": "Dynamo Y13", "genres": [], "popularity": 0}, "770sb388a8MeOngUstEFDI": {"name": "Y1hya", "genres": [], "popularity": 0}, "1Vu8dAznZPzFadikESTKhb": {"name": "Y1nka", "genres": [], "popularity": 2}, "75C6ciYpEGngvGFCQygt5P": {"name": "Y12", "genres": [], "popularity": 0}, "5ok6TpicWZokAspXsAfMLz": {"name": "Y1", "genres": [], "popularity": 0}, "1koFsQ1jA3LtD9bN8nqwSV": {"name": "Y122468", "genres": [], "popularity": 0}, "3qYbBYi6RAxrJLiaCwofm4": {"name": "Y1 MARDEL", "genres": [], "popularity": 0}, "5dtS7hsXUSajIiJJEgNv8E": {"name": "Y13", "genres": [], "popularity": 0}, "1UyNc6m5PozxSHeCDxZUN1": {"name": "y1fun9", "genres": [], "popularity": 0}, "4Mln3QYM6U7banIaJwLqZe": {"name": "Y1", "genres": [], "popularity": 0}, "2i4o9lwhikIiVt9c0DcbAF": {"name": "Y13N", "genres": [], "popularity": 0}, "5yycfDgjxK8rdf0w35wzQr": {"name": "Y1ee", "genres": [], "popularity": 0}, "7FdmRmOIMTPbGsUG6UgPk8": {"name": "Y1 DEE", "genres": [], "popularity": 0}, "5E2PuVXLF6lghqLMXIztl3": {"name": "Y17", "genres": [], "popularity": 0}, "2Ve93qIdmxXOHeLTeee1HI": {"name": "Y18", "genres": [], "popularity": 0}, "3oYsQ8ZyTNc1IKabk9I2Bp": {"name": "Y1 Leakey", "genres": [], "popularity": 0}, "1H9dCyeHRozwB0ISXHAFcd": {"name": "Y16SHALLOW", "genres": [], "popularity": 0}, "7AtlruLAxDXqnKeYfDsZmj": {"name": "Y1NEGVE", "genres": [], "popularity": 0}, "1LEUUjOmloj2yeaqCBgpvY": {"name": "Y16", "genres": [], "popularity": 0}, "35WpTMJSE3OG2znNfJZ02q": {"name": "Y11", "genres": [], "popularity": 0}, "3SA25eAIwddusdrjd22zKX": {"name": "Y1G", "genres": [], "popularity": 0}, "460EDllwy4SpeqQnkpi0rL": {"name": "Y1World", "genres": [], "popularity": 0}, "0cRwjTm96uhyYMa2MeUdmP": {"name": "y1ee", "genres": [], "popularity": 0}, "6NHvSnBX0cB3YzHXM14hw8": {"name": "Y1ee", "genres": [], "popularity": 0}, "2yUaIwoferyxbuVdQpIQZf": {"name": "Y1EE", "genres": [], "popularity": 0}, "1fAKPraC6xjaNUCoGlrCcb": {"name": "HE Y1K", "genres": [], "popularity": 0}, "7wObwVIRJWiiOKhk8gOMPC": {"name": "Y1'z", "genres": [], "popularity": 0}, "6slBJVNq60qvyAGaJvU2dp": {"name": "y1k", "genres": [], "popularity": 0}, "5z2nRbZYhWL3w7vv4PEOm7": {"name": "Y10", "genres": [], "popularity": 0}, "5dA7j1bvJAe9UvTVLyMx1f": {"name": "Y1GGSuave", "genres": [], "popularity": 0}, "5q9SoWDCu2FjJqz82iwZfO": {"name": "Y1NDAMENACE", "genres": [], "popularity": 0}, "2f8gwMKMRImSCFTkxVdCRE": {"name": "Y1K BABY", "genres": [], "popularity": 0}, "4vOzymSWT0SwBs45klY63D": {"name": "y1hya", "genres": [], "popularity": 0}, "2FAoynkrqV8MHKEOLIifWK": {"name": "Y1N", "genres": [], "popularity": 0}, "0ubHqKIM5vYMfDIT50lCTw": {"name": "y1r4ik", "genres": [], "popularity": 0}, "4V3zawliKfIQkrUJnobGSQ": {"name": "Y1eeCoyote", "genres": [], "popularity": 0}, "1A7SJ520LgGU0wZcdNnIIm": {"name": "Y1metra", "genres": [], "popularity": 0}, "4vtj4FNzYXVqTBB6CPaS1k": {"name": "Grupo Y1", "genres": [], "popularity": 0}, "470yDyXMZ0tctftUL3pKtq": {"name": "Y1mmy", "genres": [], "popularity": 0}, "5nW0wUE8rVy5pIq4UlukRl": {"name": "y1r4ik", "genres": [], "popularity": 0}, "4ND7t9FWNVcsQBSlu0y5Ic": {"name": "Y124s", "genres": [], "popularity": 0}, "0081kEpze1Wn2vDgndgxki": {"name": "Noha Y12", "genres": [], "popularity": 0}, "5yHBiRbKzxNIqcZ8ecTozi": {"name": "Y1", "genres": [], "popularity": 0}, "2opRIRU2PokFK3vrlBV0un": {"name": "Bless y16k", "genres": [], "popularity": 0}, "0dUN80iv1gqOZb9hTywncy": {"name": "Y11", "genres": [], "popularity": 0}, "0JGqvQJq14wL7xUWxFJNAn": {"name": "Y1 D-WOO", "genres": [], "popularity": 0}, "4jRCm6Kg6yfyB8H99v4uDJ": {"name": "Y1 GGSuave", "genres": [], "popularity": 0}, "4PVHeLr2EXJcq1Mj0iJ6Ha": {"name": "Dkash & Y1ee", "genres": [], "popularity": 0}, "5VOVkqbK1WHNI58t4sVNFH": {"name": "Y1ee Coyote", "genres": [], "popularity": 3}, "3JMWyNrCzXOr9DmnvrZrO1": {"name": "Y10 Da Plug", "genres": [], "popularity": 0}, "4kORogTibHkMhqbJPZG7eA": {"name": "Y1 D Danger", "genres": [], "popularity": 0}, "4eBOiLW2dwR5B8lbtaVRVg": {"name": "Y1zy \u5434\u6c82\u6cfd", "genres": [], "popularity": 0}, "2OL5FVY75CsYyhIqHJMoMK": {"name": "Y1 King Killa", "genres": [], "popularity": 0}, "7i5IHxiQtyASy7b3haQSvD": {"name": "Y1\u522b\u8dd1", "genres": [], "popularity": 0}, "4LLFdZZrEWyfCoEnZaZXXd": {"name": "Y18 Hard Driver HD", "genres": [], "popularity": 0}, "4OgGWjNPuYBu5FDFM8aaCR": {"name": "Y1 GG Suave", "genres": [], "popularity": 0}, "7BdVarRrUhoQvQXKZVhy3m": {"name": "\u675c\u5955\u5c91Y1cen", "genres": [], "popularity": 0}, "17qgQ9nK6Hw9R0g18DgTiA": {"name": "Y1 Project", "genres": [], "popularity": 0}, "3PwUOuPzUyGPXZZKnS7Pn0": {"name": "sant-y1", "genres": [], "popularity": 0}}